lattica_management/README.md
lattica_management/__init__.py
lattica_management/lattica_management.py
lattica_management-0.1.6.dist-info/LICENSE.txt
lattica_management-0.1.6.dist-info/METADATA
lattica_management-0.1.6.dist-info/WHEEL
lattica_management-0.1.6.dist-info/RECORD
