Metadata-Version: 2.3
Name: lattica-management
Version: 0.1.6
Summary: Lattica management client
License: Proprietary
Author: LatticaAI Inc.
Author-email: hello@lattica.ai
Requires-Python: >=3.10,<4.0
Classifier: License :: Other/Proprietary License
Classifier: Programming Language :: Python :: 3
Classifier: Programming Language :: Python :: 3.10
Classifier: Programming Language :: Python :: 3.11
Classifier: Programming Language :: Python :: 3.12
Classifier: Programming Language :: Python :: 3.13
Requires-Dist: lattica-common (>=0.5.5,<0.6.0)
Requires-Dist: pyyaml
Project-URL: Homepage, https://www.lattica.ai/
